{"totales":{"PorcentajeDesaparecidos":"100.00","PorcentajeLocalizados":"0.00","PorcentajeLocalizadosCV":"0.00","PorcentajeLocalizadosSV":"0.00","PorcentajeSoloDesaparecidos":"66.67","PorcentajeSoloNoLocalizados":"33.33","TotalDesaparecidos":"03","TotalGlobal":"03","TotalLocalizados":"00","TotalLocalizadosCV":"00","TotalLocalizadosSV":"00","TotalSoloDesaparecidos":"02","TotalSoloNoLocalizados":"01"},"espacial":{"Hombres":{"NEPOPUALCO":1,"SIN COLONIA DE REFERENCIA":0,"TOTOLAPAN":0},"Indeterminado":{"NEPOPUALCO":0,"SIN COLONIA DE REFERENCIA":0,"TOTOLAPAN":0},"Mujeres":{"NEPOPUALCO":0,"SIN COLONIA DE REFERENCIA":1,"TOTOLAPAN":1}},"anual":{"Hombre":{"2020":1},"Indeterminado":{"2020":0},"Mujer":{"2020":2}},"mensual_ultimo_anio":{"Hombre":{"2020-OCTUBRE":1},"Indeterminado":{"2020-OCTUBRE":0},"Mujer":{"2020-OCTUBRE":2}},"por_edad":{"Hombres":{"16":1,"18":0},"Indeterminado":{"16":0,"18":0},"Mujeres":{"16":0,"18":2}},"por_nacionalidad":{"Hombres":{"MEXICANA":1},"Indeterminado":{"MEXICANA":0},"Mujeres":{"MEXICANA":2}}}