{"totales":{"PorcentajeDesaparecidos":"30.43","PorcentajeLocalizados":"69.57","PorcentajeLocalizadosCV":"100.00","PorcentajeLocalizadosSV":"0.00","PorcentajeSoloDesaparecidos":"71.43","PorcentajeSoloNoLocalizados":"28.57","TotalDesaparecidos":"07","TotalGlobal":"23","TotalLocalizados":"16","TotalLocalizadosCV":"16","TotalLocalizadosSV":"00","TotalSoloDesaparecidos":"05","TotalSoloNoLocalizados":"02"},"espacial":{"Hombres":{"ATLATLAHUCAN":4,"EL SALTO":1,"GUADALUPANA":1,"LOS REYES":0,"RANCHO SANTA CRUZ":0,"SAN ANDRÉS":0,"SAN MIGUEL TLALTETELCO":1,"SAN SEBASTIÁN":1,"SANTA BÁRBARA":0,"SIN COLONIA DE REFERENCIA":4,"VICENTE GUERRERO":1},"Indeterminado":{"ATLATLAHUCAN":0,"EL SALTO":0,"GUADALUPANA":0,"LOS REYES":0,"RANCHO SANTA CRUZ":0,"SAN ANDRÉS":0,"SAN MIGUEL TLALTETELCO":0,"SAN SEBASTIÁN":0,"SANTA BÁRBARA":0,"SIN COLONIA DE REFERENCIA":0,"VICENTE GUERRERO":0},"Mujeres":{"ATLATLAHUCAN":0,"EL SALTO":0,"GUADALUPANA":0,"LOS REYES":1,"RANCHO SANTA CRUZ":2,"SAN ANDRÉS":1,"SAN MIGUEL TLALTETELCO":1,"SAN SEBASTIÁN":0,"SANTA BÁRBARA":1,"SIN COLONIA DE REFERENCIA":4,"VICENTE GUERRERO":0}},"anual":{"Hombre":{"1.CIFRA SIN  AÑO DE REFERENCIA":3,"2011":3,"2016":2,"2020":4,"2021":1},"Indeterminado":{"1.CIFRA SIN  AÑO DE REFERENCIA":0,"2011":0,"2016":0,"2020":0,"2021":0},"Mujer":{"1.CIFRA SIN  AÑO DE REFERENCIA":0,"2011":1,"2016":2,"2020":5,"2021":2}},"mensual_ultimo_anio":{"Hombre":{"2011-FEBRERO":1,"2011-MAYO":2,"2016-JULIO":2,"2016-JUNIO":0,"2020-ABRIL":1,"2020-AGOSTO":1,"2020-DICIEMBRE":0,"2020-FEBRERO":0,"2020-OCTUBRE":1,"2020-SEPTIEMBRE":1,"2021-ABRIL":1,"2021-ENERO":0},"Indeterminado":{"2011-FEBRERO":0,"2011-MAYO":0,"2016-JULIO":0,"2016-JUNIO":0,"2020-ABRIL":0,"2020-AGOSTO":0,"2020-DICIEMBRE":0,"2020-FEBRERO":0,"2020-OCTUBRE":0,"2020-SEPTIEMBRE":0,"2021-ABRIL":0,"2021-ENERO":0},"Mujer":{"2011-FEBRERO":0,"2011-MAYO":0,"2016-JULIO":0,"2016-JUNIO":2,"2020-ABRIL":0,"2020-AGOSTO":1,"2020-DICIEMBRE":3,"2020-FEBRERO":1,"2020-OCTUBRE":0,"2020-SEPTIEMBRE":0,"2021-ABRIL":0,"2021-ENERO":2}},"por_edad":{"Hombres":{"0":1,"1":0,"11":1,"12":0,"14":0,"15":0,"17":0,"18":0,"21":1,"24":0,"25":1,"28":1,"29":1,"30":2,"32":1,"33":0,"44":2,"80":1,"SIN EDAD DE REFERENCIA":1},"Indeterminado":{"0":0,"1":0,"11":0,"12":0,"14":0,"15":0,"17":0,"18":0,"21":0,"24":0,"25":0,"28":0,"29":0,"30":0,"32":0,"33":0,"44":0,"80":0,"SIN EDAD DE REFERENCIA":0},"Mujeres":{"0":0,"1":1,"11":0,"12":1,"14":1,"15":1,"17":2,"18":2,"21":0,"24":1,"25":0,"28":0,"29":0,"30":0,"32":0,"33":1,"44":0,"80":0,"SIN EDAD DE REFERENCIA":0}},"por_nacionalidad":{"Hombres":{"MEXICANA":13},"Indeterminado":{"MEXICANA":0},"Mujeres":{"MEXICANA":10}}}