{"totales":{"PorcentajeDesaparecidos":"48.15","PorcentajeLocalizados":"51.85","PorcentajeLocalizadosCV":"100.00","PorcentajeLocalizadosSV":"0.00","PorcentajeSoloDesaparecidos":"69.23","PorcentajeSoloNoLocalizados":"30.77","TotalDesaparecidos":"13","TotalGlobal":"27","TotalLocalizados":"14","TotalLocalizadosCV":"14","TotalLocalizadosSV":"00","TotalSoloDesaparecidos":"09","TotalSoloNoLocalizados":"04"},"espacial":{"Hombres":{"EL ÁGUILA":0,"LA CIENEGA":1,"LAS VIGAS":0,"SANTA CATARINA":1,"SIN COLONIA DE REFERENCIA":7},"Indeterminado":{"EL ÁGUILA":0,"LA CIENEGA":0,"LAS VIGAS":0,"SANTA CATARINA":0,"SIN COLONIA DE REFERENCIA":0},"Mujeres":{"EL ÁGUILA":1,"LA CIENEGA":0,"LAS VIGAS":1,"SANTA CATARINA":0,"SIN COLONIA DE REFERENCIA":16}},"anual":{"Hombre":{"1.CIFRA SIN  AÑO DE REFERENCIA":2,"2014":0,"2015":0,"2016":1,"2017":2,"2018":2,"2020":0,"2021":2},"Indeterminado":{"1.CIFRA SIN  AÑO DE REFERENCIA":0,"2014":0,"2015":0,"2016":0,"2017":0,"2018":0,"2020":0,"2021":0},"Mujer":{"1.CIFRA SIN  AÑO DE REFERENCIA":3,"2014":5,"2015":2,"2016":1,"2017":3,"2018":1,"2020":2,"2021":1}},"mensual_ultimo_anio":{"Hombre":{"2016-DICIEMBRE":0,"2017-ABRIL":0,"2017-DICIEMBRE":0,"2017-MAYO":1,"2017-OCTUBRE":1,"2018-ENERO":1,"2018-FEBRERO":1,"2020-DICIEMBRE":0,"2020-OCTUBRE":0,"2021-ABRIL":1,"2021-FEBRERO":0,"2021-MARZO":1},"Indeterminado":{"2016-DICIEMBRE":0,"2017-ABRIL":0,"2017-DICIEMBRE":0,"2017-MAYO":0,"2017-OCTUBRE":0,"2018-ENERO":0,"2018-FEBRERO":0,"2020-DICIEMBRE":0,"2020-OCTUBRE":0,"2021-ABRIL":0,"2021-FEBRERO":0,"2021-MARZO":0},"Mujer":{"2016-DICIEMBRE":1,"2017-ABRIL":1,"2017-DICIEMBRE":1,"2017-MAYO":1,"2017-OCTUBRE":0,"2018-ENERO":1,"2018-FEBRERO":0,"2020-DICIEMBRE":1,"2020-OCTUBRE":1,"2021-ABRIL":0,"2021-FEBRERO":1,"2021-MARZO":0}},"por_edad":{"Hombres":{"1":0,"10":1,"13":1,"14":1,"16":0,"17":0,"18":1,"19":0,"2":1,"20":1,"22":0,"24":0,"26":0,"27":1,"28":0,"38":1,"43":1,"47":0,"6":0,"9":0},"Indeterminado":{"1":0,"10":0,"13":0,"14":0,"16":0,"17":0,"18":0,"19":0,"2":0,"20":0,"22":0,"24":0,"26":0,"27":0,"28":0,"38":0,"43":0,"47":0,"6":0,"9":0},"Mujeres":{"1":1,"10":0,"13":0,"14":2,"16":2,"17":2,"18":0,"19":2,"2":0,"20":0,"22":1,"24":1,"26":1,"27":0,"28":1,"38":0,"43":0,"47":2,"6":2,"9":1}},"por_nacionalidad":{"Hombres":{"MEXICANA":9},"Indeterminado":{"MEXICANA":0},"Mujeres":{"MEXICANA":18}}}