{"totales":{"PorcentajeDesaparecidos":"33.33","PorcentajeLocalizados":"66.67","PorcentajeLocalizadosCV":"100.00","PorcentajeLocalizadosSV":"0.00","PorcentajeSoloDesaparecidos":"75.00","PorcentajeSoloNoLocalizados":"25.00","TotalDesaparecidos":"08","TotalGlobal":"24","TotalLocalizados":"16","TotalLocalizadosCV":"16","TotalLocalizadosSV":"00","TotalSoloDesaparecidos":"06","TotalSoloNoLocalizados":"02"},"espacial":{"Hombres":{"MORELOS":0,"SAN FELIPE OTLALTEPEC":0,"SIN COLONIA DE REFERENCIA":10},"Indeterminado":{"MORELOS":0,"SAN FELIPE OTLALTEPEC":0,"SIN COLONIA DE REFERENCIA":0},"Mujeres":{"MORELOS":1,"SAN FELIPE OTLALTEPEC":1,"SIN COLONIA DE REFERENCIA":12}},"anual":{"Hombre":{"1.CIFRA SIN  AÑO DE REFERENCIA":2,"2013":1,"2014":1,"2015":0,"2016":1,"2017":4,"2018":1},"Indeterminado":{"1.CIFRA SIN  AÑO DE REFERENCIA":0,"2013":0,"2014":0,"2015":0,"2016":0,"2017":0,"2018":0},"Mujer":{"1.CIFRA SIN  AÑO DE REFERENCIA":1,"2013":0,"2014":1,"2015":2,"2016":2,"2017":5,"2018":3}},"mensual_ultimo_anio":{"Hombre":{"2014-NOVIEMBRE":1,"2015-ENERO":0,"2015-SEPTIEMBRE":0,"2016-SEPTIEMBRE":1,"2017-ENERO":0,"2017-FEBRERO":0,"2017-MARZO":2,"2017-MAYO":1,"2017-NOVIEMBRE":1,"2018-FEBRERO":0,"2018-MAYO":0,"2018-OCTUBRE":1},"Indeterminado":{"2014-NOVIEMBRE":0,"2015-ENERO":0,"2015-SEPTIEMBRE":0,"2016-SEPTIEMBRE":0,"2017-ENERO":0,"2017-FEBRERO":0,"2017-MARZO":0,"2017-MAYO":0,"2017-NOVIEMBRE":0,"2018-FEBRERO":0,"2018-MAYO":0,"2018-OCTUBRE":0},"Mujer":{"2014-NOVIEMBRE":1,"2015-ENERO":1,"2015-SEPTIEMBRE":1,"2016-SEPTIEMBRE":2,"2017-ENERO":1,"2017-FEBRERO":1,"2017-MARZO":3,"2017-MAYO":0,"2017-NOVIEMBRE":0,"2018-FEBRERO":1,"2018-MAYO":2,"2018-OCTUBRE":0}},"por_edad":{"Hombres":{"12":0,"13":0,"14":0,"15":0,"17":2,"19":0,"20":0,"23":0,"24":2,"25":0,"3":1,"34":1,"40":0,"49":1,"55":1,"70":1,"71":1},"Indeterminado":{"12":0,"13":0,"14":0,"15":0,"17":0,"19":0,"20":0,"23":0,"24":0,"25":0,"3":0,"34":0,"40":0,"49":0,"55":0,"70":0,"71":0},"Mujeres":{"12":1,"13":1,"14":2,"15":2,"17":1,"19":2,"20":1,"23":1,"24":1,"25":1,"3":0,"34":0,"40":1,"49":0,"55":0,"70":0,"71":0}},"por_nacionalidad":{"Hombres":{"MEXICANA":10},"Indeterminado":{"MEXICANA":0},"Mujeres":{"MEXICANA":14}}}