{"totales":{"PorcentajeDesaparecidos":"33.33","PorcentajeLocalizados":"66.67","PorcentajeLocalizadosCV":"100.00","PorcentajeLocalizadosSV":"0.00","PorcentajeSoloDesaparecidos":"0.00","PorcentajeSoloNoLocalizados":"100.00","TotalDesaparecidos":"01","TotalGlobal":"03","TotalLocalizados":"02","TotalLocalizadosCV":"02","TotalLocalizadosSV":"00","TotalSoloDesaparecidos":"00","TotalSoloNoLocalizados":"01"},"espacial":{"Hombres":{"AHUATA":0,"SIN COLONIA DE REFERENCIA":1,"YAONAHUAC":0},"Indeterminado":{"AHUATA":0,"SIN COLONIA DE REFERENCIA":0,"YAONAHUAC":0},"Mujeres":{"AHUATA":1,"SIN COLONIA DE REFERENCIA":0,"YAONAHUAC":1}},"anual":{"Hombre":{"1.CIFRA SIN  AÑO DE REFERENCIA":1},"Indeterminado":{"1.CIFRA SIN  AÑO DE REFERENCIA":0},"Mujer":{"1.CIFRA SIN  AÑO DE REFERENCIA":2}},"mensual_ultimo_anio":{"Hombre":{"0-CIFRA SIN AÑO NI MES DE REFERENCIA":1},"Indeterminado":{"0-CIFRA SIN AÑO NI MES DE REFERENCIA":0},"Mujer":{"0-CIFRA SIN AÑO NI MES DE REFERENCIA":2}},"por_edad":{"Hombres":{"16":0,"26":0,"47":1},"Indeterminado":{"16":0,"26":0,"47":0},"Mujeres":{"16":1,"26":1,"47":0}},"por_nacionalidad":{"Hombres":{"MEXICANA":1},"Indeterminado":{"MEXICANA":0},"Mujeres":{"MEXICANA":2}}}