{"totales":{"PorcentajeDesaparecidos":"29.41","PorcentajeLocalizados":"70.59","PorcentajeLocalizadosCV":"91.67","PorcentajeLocalizadosSV":"8.33","PorcentajeSoloDesaparecidos":"60.00","PorcentajeSoloNoLocalizados":"40.00","TotalDesaparecidos":"05","TotalGlobal":"17","TotalLocalizados":"12","TotalLocalizadosCV":"11","TotalLocalizadosSV":"01","TotalSoloDesaparecidos":"03","TotalSoloNoLocalizados":"02"},"espacial":{"Hombres":{"DR. BELISARIO DOMÍNGUEZ":0,"EL RELICARIO":0,"ESQUIPULAS":0,"FRANCISCO I MADERO":2,"HUIXTLA CENTRO":1,"SAN FRANCISCO":0,"SIN COLONIA DE REFERENCIA":4},"Indeterminado":{"DR. BELISARIO DOMÍNGUEZ":0,"EL RELICARIO":0,"ESQUIPULAS":0,"FRANCISCO I MADERO":0,"HUIXTLA CENTRO":0,"SAN FRANCISCO":0,"SIN COLONIA DE REFERENCIA":0},"Mujeres":{"DR. BELISARIO DOMÍNGUEZ":1,"EL RELICARIO":1,"ESQUIPULAS":1,"FRANCISCO I MADERO":0,"HUIXTLA CENTRO":0,"SAN FRANCISCO":1,"SIN COLONIA DE REFERENCIA":6}},"anual":{"Hombre":{"2009":0,"2011":0,"2013":1,"2014":0,"2015":0,"2016":0,"2018":1,"2019":3,"2020":2},"Indeterminado":{"2009":0,"2011":0,"2013":0,"2014":0,"2015":0,"2016":0,"2018":0,"2019":0,"2020":0},"Mujer":{"2009":1,"2011":1,"2013":1,"2014":3,"2015":1,"2016":1,"2018":0,"2019":0,"2020":2}},"mensual_ultimo_anio":{"Hombre":{"2013-MARZO":1,"2013-MAYO":0,"2014-JULIO":0,"2014-NOVIEMBRE":0,"2015-ABRIL":0,"2016-JUNIO":0,"2018-DICIEMBRE":1,"2019-AGOSTO":1,"2019-OCTUBRE":1,"2019-SEPTIEMBRE":1,"2020-AGOSTO":0,"2020-MAYO":2},"Indeterminado":{"2013-MARZO":0,"2013-MAYO":0,"2014-JULIO":0,"2014-NOVIEMBRE":0,"2015-ABRIL":0,"2016-JUNIO":0,"2018-DICIEMBRE":0,"2019-AGOSTO":0,"2019-OCTUBRE":0,"2019-SEPTIEMBRE":0,"2020-AGOSTO":0,"2020-MAYO":0},"Mujer":{"2013-MARZO":0,"2013-MAYO":1,"2014-JULIO":2,"2014-NOVIEMBRE":1,"2015-ABRIL":1,"2016-JUNIO":1,"2018-DICIEMBRE":0,"2019-AGOSTO":0,"2019-OCTUBRE":0,"2019-SEPTIEMBRE":0,"2020-AGOSTO":2,"2020-MAYO":0}},"por_edad":{"Hombres":{"0":0,"12":0,"14":0,"15":1,"16":0,"17":0,"2":2,"20":0,"24":0,"28":1,"32":1,"33":1,"5":1,"82":0},"Indeterminado":{"0":0,"12":0,"14":0,"15":0,"16":0,"17":0,"2":0,"20":0,"24":0,"28":0,"32":0,"33":0,"5":0,"82":0},"Mujeres":{"0":1,"12":1,"14":1,"15":1,"16":1,"17":1,"2":0,"20":1,"24":1,"28":0,"32":1,"33":0,"5":0,"82":1}},"por_nacionalidad":{"Hombres":{"GUATEMALTECA":0,"MEXICANA":7},"Indeterminado":{"GUATEMALTECA":0,"MEXICANA":0},"Mujeres":{"GUATEMALTECA":1,"MEXICANA":9}}}