{"totales":{"PorcentajeDesaparecidos":"31.65","PorcentajeLocalizados":"68.35","PorcentajeLocalizadosCV":"97.70","PorcentajeLocalizadosSV":"2.30","PorcentajeSoloDesaparecidos":"87.06","PorcentajeSoloNoLocalizados":"12.94","TotalDesaparecidos":"201","TotalGlobal":"635","TotalLocalizados":"434","TotalLocalizadosCV":"424","TotalLocalizadosSV":"10","TotalSoloDesaparecidos":"175","TotalSoloNoLocalizados":"26"},"espacial":{"Hombres":{"10 DE MAYO":5,"1° DE MAYO":0,"20 DE NOVIEMBRE":11,"4 ÁRBOLES":0,"7 DE JULIO":1,"ADOLFO LÓPEZ MATEOS":6,"AERONÁUTICA MILITAR":3,"AEROPUERTO INTERNACIONAL DE LA CIUDAD DE MÉXICO":3,"AMPLIACIÓN AVIACIÓN CIVIL":1,"AMPLIACIÓN CARACOL":0,"AMPLIACIÓN MICHOACANA":1,"AMPLIACIÓN PENITENCIARIA":1,"AQUILES SERDÁN":5,"ARENAL 1A SECCIÓN":4,"ARENAL 3A SECCIÓN":1,"ARENAL 4A SECCIÓN":4,"ARTES GRAFICAS":3,"AVIACIÓN CIVIL":8,"AZTECA":1,"CARACOL":4,"CUCHILLA PANTITLAN":2,"DAMIÁN CARMONA":2,"DEL PARQUE":3,"EMILIANO ZAPATA":0,"EMILIO CARRANZA":2,"ESCUELA DE TIRO":1,"FEDERAL":7,"FELIPE ÁNGELES":0,"GENERAL IGNACIO ZARAGOZA":9,"INDUSTRIAL PUERTO AÉREO":2,"JAMAICA":3,"JANITZIO":4,"JARDÍN BALBUENA":10,"LORENZO BOTURINI":0,"MAGDALENA MIXIHUCA":1,"MERCED BALBUENA":16,"MICHOACANA":0,"MOCTEZUMA 1A SECCIÓN":7,"MOCTEZUMA 2A SECCIÓN":10,"MORELOS":13,"NICOLÁS BRAVO":0,"PENITENCIARIA":1,"PENSADOR MEXICANO":6,"PEÑÓN DE LOS BAÑOS":17,"POPULAR RASTRO":1,"PROGRESISTA":3,"PUEBLA":1,"REVOLUCIÓN":2,"ROMERO RUBIO":7,"SANTA CRUZ AVIACIÓN":1,"SEVILLA":0,"SIMÓN BOLÍVAR":2,"SIN COLONIA DE REFERENCIA":117,"VALENTÍN GÓMEZ FARIAS":9,"VALLE GÓMEZ":3,"ZONA CENTRO":8,"ÁLVARO OBREGÓN":2},"Indeterminado":{"10 DE MAYO":0,"1° DE MAYO":0,"20 DE NOVIEMBRE":0,"4 ÁRBOLES":0,"7 DE JULIO":0,"ADOLFO LÓPEZ MATEOS":0,"AERONÁUTICA MILITAR":0,"AEROPUERTO INTERNACIONAL DE LA CIUDAD DE MÉXICO":0,"AMPLIACIÓN AVIACIÓN CIVIL":0,"AMPLIACIÓN CARACOL":0,"AMPLIACIÓN MICHOACANA":0,"AMPLIACIÓN PENITENCIARIA":0,"AQUILES SERDÁN":1,"ARENAL 1A SECCIÓN":0,"ARENAL 3A SECCIÓN":0,"ARENAL 4A SECCIÓN":0,"ARTES GRAFICAS":0,"AVIACIÓN CIVIL":0,"AZTECA":0,"CARACOL":0,"CUCHILLA PANTITLAN":0,"DAMIÁN CARMONA":0,"DEL PARQUE":0,"EMILIANO ZAPATA":0,"EMILIO CARRANZA":0,"ESCUELA DE TIRO":0,"FEDERAL":0,"FELIPE ÁNGELES":0,"GENERAL IGNACIO ZARAGOZA":0,"INDUSTRIAL PUERTO AÉREO":0,"JAMAICA":0,"JANITZIO":0,"JARDÍN BALBUENA":0,"LORENZO BOTURINI":0,"MAGDALENA MIXIHUCA":0,"MERCED BALBUENA":0,"MICHOACANA":0,"MOCTEZUMA 1A SECCIÓN":0,"MOCTEZUMA 2A SECCIÓN":0,"MORELOS":0,"NICOLÁS BRAVO":0,"PENITENCIARIA":0,"PENSADOR MEXICANO":1,"PEÑÓN DE LOS BAÑOS":0,"POPULAR RASTRO":0,"PROGRESISTA":0,"PUEBLA":0,"REVOLUCIÓN":0,"ROMERO RUBIO":0,"SANTA CRUZ AVIACIÓN":0,"SEVILLA":0,"SIMÓN BOLÍVAR":0,"SIN COLONIA DE REFERENCIA":4,"VALENTÍN GÓMEZ FARIAS":0,"VALLE GÓMEZ":0,"ZONA CENTRO":0,"ÁLVARO OBREGÓN":0},"Mujeres":{"10 DE MAYO":9,"1° DE MAYO":1,"20 DE NOVIEMBRE":3,"4 ÁRBOLES":1,"7 DE JULIO":0,"ADOLFO LÓPEZ MATEOS":4,"AERONÁUTICA MILITAR":6,"AEROPUERTO INTERNACIONAL DE LA CIUDAD DE MÉXICO":0,"AMPLIACIÓN AVIACIÓN CIVIL":0,"AMPLIACIÓN CARACOL":1,"AMPLIACIÓN MICHOACANA":2,"AMPLIACIÓN PENITENCIARIA":3,"AQUILES SERDÁN":1,"ARENAL 1A SECCIÓN":4,"ARENAL 3A SECCIÓN":1,"ARENAL 4A SECCIÓN":2,"ARTES GRAFICAS":4,"AVIACIÓN CIVIL":8,"AZTECA":1,"CARACOL":3,"CUCHILLA PANTITLAN":3,"DAMIÁN CARMONA":3,"DEL PARQUE":4,"EMILIANO ZAPATA":1,"EMILIO CARRANZA":0,"ESCUELA DE TIRO":0,"FEDERAL":4,"FELIPE ÁNGELES":5,"GENERAL IGNACIO ZARAGOZA":2,"INDUSTRIAL PUERTO AÉREO":1,"JAMAICA":3,"JANITZIO":1,"JARDÍN BALBUENA":10,"LORENZO BOTURINI":2,"MAGDALENA MIXIHUCA":2,"MERCED BALBUENA":11,"MICHOACANA":2,"MOCTEZUMA 1A SECCIÓN":5,"MOCTEZUMA 2A SECCIÓN":14,"MORELOS":10,"NICOLÁS BRAVO":1,"PENITENCIARIA":0,"PENSADOR MEXICANO":5,"PEÑÓN DE LOS BAÑOS":3,"POPULAR RASTRO":0,"PROGRESISTA":0,"PUEBLA":5,"REVOLUCIÓN":4,"ROMERO RUBIO":6,"SANTA CRUZ AVIACIÓN":1,"SEVILLA":1,"SIMÓN BOLÍVAR":3,"SIN COLONIA DE REFERENCIA":105,"VALENTÍN GÓMEZ FARIAS":2,"VALLE GÓMEZ":9,"ZONA CENTRO":5,"ÁLVARO OBREGÓN":0}},"anual":{"Hombre":{"1.CIFRA SIN  AÑO DE REFERENCIA":15,"1972":1,"1996":0,"1998":1,"2001":1,"2008":1,"2009":5,"2010":19,"2011":22,"2012":32,"2013":32,"2014":6,"2015":5,"2016":2,"2018":4,"2019":114,"2020":59,"2021":21},"Indeterminado":{"1.CIFRA SIN  AÑO DE REFERENCIA":6,"1972":0,"1996":0,"1998":0,"2001":0,"2008":0,"2009":0,"2010":0,"2011":0,"2012":0,"2013":0,"2014":0,"2015":0,"2016":0,"2018":0,"2019":0,"2020":0,"2021":0},"Mujer":{"1.CIFRA SIN  AÑO DE REFERENCIA":9,"1972":0,"1996":1,"1998":0,"2001":0,"2008":0,"2009":12,"2010":14,"2011":22,"2012":19,"2013":37,"2014":7,"2015":4,"2016":0,"2018":5,"2019":95,"2020":50,"2021":14}},"mensual_ultimo_anio":{"Hombre":{"2020-AGOSTO":6,"2020-DICIEMBRE":4,"2020-NOVIEMBRE":5,"2020-OCTUBRE":6,"2020-SEPTIEMBRE":5,"2021-ABRIL":3,"2021-ENERO":3,"2021-FEBRERO":5,"2021-JULIO":1,"2021-JUNIO":3,"2021-MARZO":3,"2021-MAYO":3},"Indeterminado":{"2020-AGOSTO":0,"2020-DICIEMBRE":0,"2020-NOVIEMBRE":0,"2020-OCTUBRE":0,"2020-SEPTIEMBRE":0,"2021-ABRIL":0,"2021-ENERO":0,"2021-FEBRERO":0,"2021-JULIO":0,"2021-JUNIO":0,"2021-MARZO":0,"2021-MAYO":0},"Mujer":{"2020-AGOSTO":3,"2020-DICIEMBRE":0,"2020-NOVIEMBRE":4,"2020-OCTUBRE":2,"2020-SEPTIEMBRE":6,"2021-ABRIL":1,"2021-ENERO":0,"2021-FEBRERO":1,"2021-JULIO":4,"2021-JUNIO":1,"2021-MARZO":1,"2021-MAYO":6}},"por_edad":{"Hombres":{"1":2,"10":2,"11":3,"12":4,"13":7,"14":7,"15":5,"16":8,"17":8,"18":8,"19":4,"2":1,"20":11,"21":7,"22":5,"23":10,"24":10,"25":5,"26":4,"27":3,"28":7,"29":6,"3":0,"30":8,"31":7,"32":10,"33":9,"34":9,"35":5,"36":5,"37":7,"38":7,"39":9,"4":2,"40":6,"41":2,"42":4,"43":6,"44":8,"45":3,"46":1,"47":5,"48":4,"49":3,"5":2,"50":5,"51":0,"52":3,"53":4,"54":6,"55":5,"56":0,"57":4,"58":3,"59":3,"6":2,"60":1,"61":1,"62":2,"63":0,"64":4,"65":3,"66":0,"67":3,"68":3,"69":2,"7":1,"70":3,"71":1,"72":4,"73":2,"74":0,"75":1,"76":3,"77":2,"78":1,"79":1,"8":3,"80":0,"81":0,"84":2,"85":0,"86":1,"87":1,"88":2,"9":2,"90":2,"91":1,"93":1,"SIN EDAD DE REFERENCIA":3},"Indeterminado":{"1":0,"10":0,"11":0,"12":0,"13":0,"14":0,"15":0,"16":0,"17":0,"18":0,"19":1,"2":0,"20":0,"21":0,"22":0,"23":0,"24":0,"25":0,"26":1,"27":0,"28":0,"29":0,"3":0,"30":0,"31":0,"32":0,"33":0,"34":0,"35":0,"36":0,"37":0,"38":0,"39":1,"4":0,"40":0,"41":0,"42":0,"43":1,"44":0,"45":0,"46":0,"47":0,"48":0,"49":0,"5":0,"50":0,"51":0,"52":0,"53":1,"54":0,"55":0,"56":0,"57":0,"58":0,"59":0,"6":0,"60":0,"61":0,"62":0,"63":0,"64":0,"65":0,"66":0,"67":0,"68":0,"69":0,"7":0,"70":0,"71":0,"72":1,"73":0,"74":0,"75":0,"76":0,"77":0,"78":0,"79":0,"8":0,"80":0,"81":0,"84":0,"85":0,"86":0,"87":0,"88":0,"9":0,"90":0,"91":0,"93":0,"SIN EDAD DE REFERENCIA":0},"Mujeres":{"1":3,"10":3,"11":3,"12":1,"13":22,"14":19,"15":26,"16":24,"17":14,"18":16,"19":8,"2":1,"20":6,"21":9,"22":7,"23":9,"24":5,"25":5,"26":3,"27":5,"28":5,"29":4,"3":3,"30":4,"31":4,"32":2,"33":3,"34":5,"35":5,"36":1,"37":3,"38":1,"39":3,"4":2,"40":3,"41":1,"42":0,"43":1,"44":2,"45":2,"46":2,"47":3,"48":1,"49":1,"5":5,"50":0,"51":2,"52":0,"53":2,"54":0,"55":2,"56":1,"57":1,"58":1,"59":0,"6":0,"60":0,"61":0,"62":1,"63":2,"64":1,"65":2,"66":2,"67":1,"68":0,"69":0,"7":1,"70":0,"71":0,"72":0,"73":0,"74":2,"75":1,"76":0,"77":1,"78":0,"79":1,"8":2,"80":1,"81":1,"84":1,"85":1,"86":0,"87":1,"88":0,"9":1,"90":0,"91":0,"93":0,"SIN EDAD DE REFERENCIA":2}},"por_nacionalidad":{"Hombres":{"ARGENTINA":1,"BOLIVIANA":0,"BRASILENA":1,"COLOMBIANA":2,"ESTADOUNIDENSE":2,"GUATEMALTECA":1,"HINDU":2,"MEXICANA":321,"PAQUISTANI":1,"POLACA":1,"SE DESCONOCE":8},"Indeterminado":{"ARGENTINA":0,"BOLIVIANA":0,"BRASILENA":0,"COLOMBIANA":0,"ESTADOUNIDENSE":0,"GUATEMALTECA":0,"HINDU":0,"MEXICANA":0,"PAQUISTANI":0,"POLACA":0,"SE DESCONOCE":6},"Mujeres":{"ARGENTINA":0,"BOLIVIANA":1,"BRASILENA":0,"COLOMBIANA":2,"ESTADOUNIDENSE":0,"GUATEMALTECA":0,"HINDU":0,"MEXICANA":276,"PAQUISTANI":0,"POLACA":0,"SE DESCONOCE":10}}}